README.md
pyproject.toml
setup.py
src/Examples/__init__.py
src/Examples/examples.py
src/GF/GGG.py
src/GF/GMM.py
src/GF/GNG.py
src/GF/GraphTools.py
src/GF/RGM.py
src/GF/SOM.py
src/GF/__init__.py
src/PersistentHomology/FilteredSimplicialComplexes.py
src/PersistentHomology/PersLay.py
src/PersistentHomology/PersistenceDiagram.py
src/PersistentHomology/PersistenceImage.py
src/PersistentHomology/PersistenceLandscapes.py
src/PersistentHomology/TopologicalAutoencoder.py
src/PersistentHomology/__init__.py
src/TML_toolkit.egg-info/PKG-INFO
src/TML_toolkit.egg-info/SOURCES.txt
src/TML_toolkit.egg-info/dependency_links.txt
src/TML_toolkit.egg-info/requires.txt
src/TML_toolkit.egg-info/top_level.txt