Metadata-Version: 2.1
Name: TML-toolkit
Version: 1.0.7
Summary: Tools for topological machine learning
Home-page: UNKNOWN
Author: Sigurd Solberg
Author-email: sigroll@gmail.com
License: UNKNOWN
Platform: UNKNOWN
